iflow_mcp_searxng-0.1.0.dist-info/licenses/LICENSE
mcp_searxng/__init__.py
mcp_searxng/main.py
mcp_searxng/prompts.py
mcp_searxng/search.py
mcp_searxng/server.py
mcp_searxng/tools.py
iflow_mcp_searxng-0.1.0.dist-info/METADATA
iflow_mcp_searxng-0.1.0.dist-info/WHEEL
iflow_mcp_searxng-0.1.0.dist-info/entry_points.txt
iflow_mcp_searxng-0.1.0.dist-info/top_level.txt
iflow_mcp_searxng-0.1.0.dist-info/RECORD
