Metadata-Version: 2.4
Name: iflow-mcp-searxng
Version: 0.1.0
Summary: MCP server for connecting agentic systems to search systems via searXNG
Author-email: TerminalMan <84923604+SecretiveShell@users.noreply.github.com>
Requires-Python: >=3.12
License-File: LICENSE
Requires-Dist: httpx>=0.28.1
Requires-Dist: mcp>=1.1.2
Requires-Dist: pydantic>=2.10.3
Dynamic: license-file
